EPOS/__init__.py
EPOS/analytics.py
EPOS/cgs.py
EPOS/classes.py
EPOS/fitfunctions.py
EPOS/kepler.py
EPOS/massradius.py
EPOS/multi.py
EPOS/occurrence.py
EPOS/pfmodel_old.py
EPOS/population.py
EPOS/regression.py
EPOS/run.py
EPOS/rv.py
EPOS/save.py
EPOS/scripts.py
EPOS/files/.DS_Store
EPOS/files/DR2PapTable1.txt
EPOS/files/DR2PapTable2.txt
EPOS/files/KOI.Q16.epos.F.npz
EPOS/files/KOI.Q16.epos.G.npz
EPOS/files/KOI.Q16.epos.K.npz
EPOS/files/KOI.Q16.epos.M.npz
EPOS/files/KOI.Q16.epos.all.npz
EPOS/files/Mayor2011.csv
EPOS/files/completeness.Q16.epos.F.npz
EPOS/files/completeness.Q16.epos.G.npz
EPOS/files/completeness.Q16.epos.K.npz
EPOS/files/completeness.Q16.epos.M.npz
EPOS/files/completeness.Q16.epos.all.npz
EPOS/files/completeness.dr25.F.gaia-r1.npz
EPOS/files/completeness.dr25.F.huber.npz
EPOS/files/completeness.dr25.G.gaia-r1.npz
EPOS/files/completeness.dr25.G.huber.npz
EPOS/files/completeness.dr25.K.gaia-r1.npz
EPOS/files/completeness.dr25.K.huber.npz
EPOS/files/completeness.dr25.M.gaia-r1.npz
EPOS/files/completeness.dr25.M.huber.npz
EPOS/files/completeness.dr25.all.gaia-r1.npz
EPOS/files/completeness.dr25.all.huber.npz
EPOS/files/completeness.dr25.binary.gaia-r1.npz
EPOS/files/completeness.dr25.dwarfs.gaia-r1.npz
EPOS/files/completeness.dr25.dwarfs.huber.npz
EPOS/files/completeness.dr25.giants.gaia-r1.npz
EPOS/files/completeness.dr25.giants.huber.npz
EPOS/files/completeness.dr25.subgiants.gaia-r1.npz
EPOS/files/completeness.dr25.subgiants.huber.npz
EPOS/files/mayor_completeness.txt
EPOS/files/q1_q17_dr25_koi.tbl
EPOS/plot/__init__.py
EPOS/plot/architecture.py
EPOS/plot/helpers.py
EPOS/plot/input.py
EPOS/plot/massradius.py
EPOS/plot/mcmc.py
EPOS/plot/model.py
EPOS/plot/multi.py
EPOS/plot/occurrence.py
EPOS/plot/output.py
EPOS/plot/parametric.py
EPOS/plot/periodradius.py
EPOS/plot/survey.py
EPOS/plot/workflow.py
EPOS/scriptdir/examples/example_1_parametric_mode.py
EPOS/scriptdir/examples/example_2_multiplanet_mode.py
epospy-3.0.2.dist-info/METADATA
epospy-3.0.2.dist-info/WHEEL
epospy-3.0.2.dist-info/top_level.txt
epospy-3.0.2.dist-info/RECORD
