Metadata-Version: 2.1
Name: epospy
Version: 3.0.2
Summary: the Exoplanet Population Observation Simulator
Home-page: https://github.com/GijsMulders/epos
Author: Gijs Mulders
Author-email: gdmulders@gmail.com
License: MIT
Platform: UNKNOWN
Classifier: Programming Language :: Python :: 3.6
Classifier: License :: OSI Approved :: MIT License
Requires-Dist: pytest (>=2.8)
Requires-Dist: numpy (>=1.13)
Requires-Dist: scipy
Requires-Dist: matplotlib (>=2.0)
Requires-Dist: astropy
Requires-Dist: emcee (>=2.0)
Requires-Dist: corner (>=2.0)
Requires-Dist: h5py
Requires-Dist: shapely
Requires-Dist: tqdm
